README.rst
inventory/__init__.py
inventory/admin.py
inventory/forms.py
inventory/models.py
inventory/urls.py
inventory/views.py
inventory/fixtures/inventory_starter_kit.json
inventory/migrations/0001_initial.py
inventory/migrations/0001_squashed_0003_auto_20150626_1807.py
inventory/migrations/0002_auto_20150626_1805.py
inventory/migrations/0002_auto_20170623_1716.py
inventory/migrations/0003_add_vendor_email.py
inventory/migrations/0003_auto_20150626_1807.py
inventory/migrations/0004_alter_category_id_alter_item_id_and_more.py
inventory/migrations/0005_rename_ptao_account_alter_account_options_and_more.py
inventory/migrations/0006_rename_ptao_order_account.py
inventory/migrations/0007_remove_duplicates.py
inventory/migrations/0008_add_uniqueness_constraints.py
inventory/migrations/0009_alter_order_order_date.py
inventory/migrations/0010_alter_order_options_rename_created_order_created_at_and_more.py
inventory/migrations/0011_remove_item_date_added_item_created_at.py
inventory/migrations/0012_alter_order_ordered_on.py
inventory/migrations/0013_rename_ordered_by_order_placed_by_and_more.py
inventory/migrations/0014_remove_order_placed_by_order_requested_by.py
inventory/migrations/0015_auto_20250811_1413.py
inventory/migrations/0016_rename_expires_account_expires_on_and_more.py
inventory/migrations/__init__.py
inventory/templates/base_view.html
inventory/templates/inventory/base.html
inventory/templates/inventory/index.html
inventory/templates/inventory/item.html
inventory/templates/inventory/item_entry.html
inventory/templates/inventory/item_list.html
inventory/templates/inventory/order.html
inventory/templates/inventory/order_entry.html
inventory/templates/inventory/order_list.html
inventory/templates/inventory/order_mark_placed.html
inventory/templates/inventory/order_table.html
inventory/templates/inventory/orderitem_confirm_delete.html
inventory/templates/inventory/orderitem_mark_received.html
django_lab_inventory-0.6.0.dist-info/METADATA
django_lab_inventory-0.6.0.dist-info/WHEEL
django_lab_inventory-0.6.0.dist-info/licenses/COPYING
django_lab_inventory-0.6.0.dist-info/RECORD
